src/Terminal_game.py
src/__init__.py
terminal_game_MI0-0.0.1.dist-info/LICENSE
terminal_game_MI0-0.0.1.dist-info/METADATA
terminal_game_MI0-0.0.1.dist-info/WHEEL
terminal_game_MI0-0.0.1.dist-info/entry_points.txt
terminal_game_MI0-0.0.1.dist-info/top_level.txt
terminal_game_MI0-0.0.1.dist-info/RECORD
